pyparams/__init__.py
pyparams/module.py
pyparams/modules_parser.py
pyparams/pyparam.py
pyparams/pyparam_fn.py
pyparams/pyparam_parser.py
pyparams/utils.py
python_params-0.1.1.data/scripts/pyparams
python_params-0.1.1.dist-info/LICENSE
python_params-0.1.1.dist-info/METADATA
python_params-0.1.1.dist-info/WHEEL
python_params-0.1.1.dist-info/top_level.txt
python_params-0.1.1.dist-info/RECORD
